Metadata-Version: 2.4
Name: plot_serializer
Version: 0.2.3
Summary: A simple tool for serializing scientific diagram to (FAIR) data.
Author-email: Michaela Lestakova <michaela.lestakova@tu-darmstadt.de>, Ning Xia <ning.xia@tu-darmstadt.de>
License: MIT License
Project-URL: repository, https://git.rwth-aachen.de/rdm-tools/plot-serializer
Project-URL: documentation, https://plot-serializer.readthedocs.io/en/latest/
Keywords: rdm,plot
Classifier: License :: OSI Approved :: MIT License
Classifier: Programming Language :: Python :: 3
Classifier: Programming Language :: Python :: 3.9
Classifier: Programming Language :: Python :: 3 :: Only
Requires-Python: >=3.9
License-File: LICENSE
Requires-Dist: numpy
Requires-Dist: pandas
Requires-Dist: matplotlib>=3.9
Requires-Dist: rdflib
Requires-Dist: pydantic
Requires-Dist: rocrate
Provides-Extra: dev
Requires-Dist: ruff; extra == "dev"
Provides-Extra: test
Requires-Dist: pytest>=7.1.2; extra == "test"
Requires-Dist: pytest-cov>=3.0.0; extra == "test"
Requires-Dist: mypy>=0.971; extra == "test"
Requires-Dist: pandas-stubs>=1.4.3.220822; extra == "test"
Requires-Dist: types-tqdm>=4.64.5; extra == "test"
Requires-Dist: types-pytz>=2022.2.1.0; extra == "test"
Provides-Extra: doc
Requires-Dist: sphinx>=5.1.1; extra == "doc"
Requires-Dist: sphinx-rtd-theme>=1.0.0; extra == "doc"
Requires-Dist: sphinx-autoapi; extra == "doc"
Dynamic: license-file
